[
    {
        "name" : "Homepage",
        "url" : "menu/homepage",
        "component": "HomepageComponent",
        "icon": "home-outline"
    },
    {
        "name" : "Trainings",
        "url" : "menu/register-training",
        "component": "RegisterTrainingComponent",
        "icon": "barbell-outline"
    },
    {
        "name" : "Report",
        "url" : "menu/report",
        "component": null,
        "icon": "stats-chart-outline"
    },
    {
        "name" : "Food history",
        "url" : "menu/food-history",
        "component": "FoodHistoryComponent",
        "icon": "nutrition-outline"
    },
    {
        "name" : "Gallery",
        "url" : "menu/gallery",
        "component": "GalleryComponent",
        "icon": "images-outline"
    }  
]